sparsedat/Data_Type.py
sparsedat/Metadata_Type.py
sparsedat/Output_Mode.py
sparsedat/Sparse_Data_Table.py
sparsedat/__init__.py
sparsedat/wrappers.py
sparsedat-1.0.0a12.dist-info/DESCRIPTION.rst
sparsedat-1.0.0a12.dist-info/METADATA
sparsedat-1.0.0a12.dist-info/RECORD
sparsedat-1.0.0a12.dist-info/WHEEL
sparsedat-1.0.0a12.dist-info/metadata.json
sparsedat-1.0.0a12.dist-info/top_level.txt
